sigma/backends/elasticsearch/__init__.py
sigma/backends/elasticsearch/elasticsearch_elastalert.py
sigma/backends/elasticsearch/elasticsearch_eql.py
sigma/backends/elasticsearch/elasticsearch_esql.py
sigma/backends/elasticsearch/elasticsearch_lucene.py
sigma/pipelines/elasticsearch/__init__.py
sigma/pipelines/elasticsearch/kubernetes.py
sigma/pipelines/elasticsearch/windows.py
sigma/pipelines/elasticsearch/zeek.py
pysigma_backend_elasticsearch-2.0.1.dist-info/METADATA
pysigma_backend_elasticsearch-2.0.1.dist-info/WHEEL
pysigma_backend_elasticsearch-2.0.1.dist-info/licenses/LICENSE
pysigma_backend_elasticsearch-2.0.1.dist-info/RECORD
