Metadata-Version: 2.4
Name: pySigma-backend-elasticsearch
Version: 2.0.1
Summary: pySigma Elasticsearch backend supporting Lucene, ES|QL (with correlations) and EQL queries
License: LGPL-3.0-only
License-File: LICENSE
Author: Thomas Patzke
Author-email: thomas@patzke.org
Requires-Python: >=3.10,<4.0
Classifier: License :: OSI Approved :: GNU Lesser General Public License v3 (LGPLv3)
Classifier: Programming Language :: Python :: 3
Classifier: Programming Language :: Python :: 3.10
Classifier: Programming Language :: Python :: 3.11
Classifier: Programming Language :: Python :: 3.12
Classifier: Programming Language :: Python :: 3.13
Classifier: Programming Language :: Python :: 3.14
Requires-Dist: pysigma (>=1.0.2,<2)
Requires-Dist: pyyaml (>=6.0.3,<7.0.0)
Project-URL: Repository, https://github.com/SigmaHQ/pySigma-backend-elasticsearch
